asutheme/__init__.py
asutheme/context_processors.py
asutheme/models.py
asutheme/static/favicon.ico
asutheme/static/asutheme/asu/css/bootstrap-asu.css
asutheme/static/asutheme/asu/css/bootstrap-asu.css.map
asutheme/static/asutheme/asu/css/bootstrap-asu.min.css
asutheme/static/asutheme/asu/fonts/FontAwesome.otf
asutheme/static/asutheme/asu/fonts/fontawesome-webfont.eot
asutheme/static/asutheme/asu/fonts/fontawesome-webfont.svg
asutheme/static/asutheme/asu/fonts/fontawesome-webfont.ttf
asutheme/static/asutheme/asu/fonts/fontawesome-webfont.woff
asutheme/static/asutheme/asu/img/favicon/apple-touch-icon-114x114.png
asutheme/static/asutheme/asu/img/favicon/apple-touch-icon-120x120.png
asutheme/static/asutheme/asu/img/favicon/apple-touch-icon-144x144.png
asutheme/static/asutheme/asu/img/favicon/apple-touch-icon-152x152.png
asutheme/static/asutheme/asu/img/favicon/apple-touch-icon-57x57.png
asutheme/static/asutheme/asu/img/favicon/apple-touch-icon-60x60.png
asutheme/static/asutheme/asu/img/favicon/apple-touch-icon-72x72.png
asutheme/static/asutheme/asu/img/favicon/apple-touch-icon-76x76.png
asutheme/static/asutheme/asu/img/favicon/favicon-128.png
asutheme/static/asutheme/asu/img/favicon/favicon-16x16.png
asutheme/static/asutheme/asu/img/favicon/favicon-196x196.png
asutheme/static/asutheme/asu/img/favicon/favicon-32x32.png
asutheme/static/asutheme/asu/img/favicon/favicon-96x96.png
asutheme/static/asutheme/asu/img/favicon/favicon.ico
asutheme/static/asutheme/asu/img/favicon/mstile-144x144.png
asutheme/static/asutheme/asu/img/favicon/mstile-150x150.png
asutheme/static/asutheme/asu/img/favicon/mstile-310x150.png
asutheme/static/asutheme/asu/img/favicon/mstile-310x310.png
asutheme/static/asutheme/asu/img/favicon/mstile-70x70.png
asutheme/static/asutheme/asu/js/bootstrap-asu.js
asutheme/static/asutheme/asu/js/bootstrap-asu.min.js
asutheme/static/asutheme/asu/js/bootstrap-asu.min.js.map
asutheme/static/asutheme/bootstrap/css/bootstrap-theme.css
django_asutheme3-0.3.0.dist-info/LICENSE
django_asutheme3-0.3.0.dist-info/METADATA
django_asutheme3-0.3.0.dist-info/WHEEL
django_asutheme3-0.3.0.dist-info/top_level.txt
django_asutheme3-0.3.0.dist-info/RECORD
