Metadata-Version: 2.1
Name: django-asutheme3
Version: 0.3.0
Summary: Base templates for Django that adhere to ASU Web Standards.
Home-page: https://github.com/asulibraries/django-asutheme
Author: Matt Cordial
Author-email: matt.cordial@asu.edu
License: Apache 2.0
Keywords: Arizona State University
Platform: UNKNOWN
Classifier: Development Status :: 4 - Beta
Classifier: Framework :: Django
Classifier: License :: Free for non-commercial use
Classifier: Intended Audience :: Developers
Classifier: Operating System :: OS Independent
Classifier: Programming Language :: Python
Classifier: Programming Language :: Python :: 2.5
Classifier: Programming Language :: Python :: 2.6
Classifier: Programming Language :: Python :: 2.7
Classifier: Programming Language :: Python :: 3.2
Classifier: Programming Language :: Python :: 3.3
Classifier: Programming Language :: Python :: 3.4
Classifier: Environment :: Web Environment
Classifier: Topic :: Software Development :: User Interfaces
License-File: LICENSE
